linp.py
linp-0.0.1.dist-info/METADATA
linp-0.0.1.dist-info/WHEEL
linp-0.0.1.dist-info/top_level.txt
linp-0.0.1.dist-info/RECORD
